clevdebug/__init__.py
clevdebug/clevdebug.py
clevdebug-0.0.2.dist-info/LICENSE.txt
clevdebug-0.0.2.dist-info/METADATA
clevdebug-0.0.2.dist-info/WHEEL
clevdebug-0.0.2.dist-info/top_level.txt
clevdebug-0.0.2.dist-info/RECORD
