Metadata-Version: 2.1
Name: clevdebug
Version: 0.0.2
Summary: Debugger as decorator for functions and methods
Home-page: https://github.com/bauyrzhanospan/cleverest_debugger
Author: Bauyrzhan Ospan, CEO "Cleverest Technologies LLP"
Author-email: main@cleverest.tech
License: MIT
Platform: Any
Classifier: Development Status :: 5 - Production/Stable
Classifier: Intended Audience :: Developers
Classifier: License :: OSI Approved :: MIT License
Classifier: Operating System :: OS Independent
Classifier: Topic :: Software Development :: Debuggers
Classifier: Topic :: Software Development :: Libraries :: Python Modules
Classifier: Programming Language :: Python :: 3
Classifier: Programming Language :: Python :: 3.9
License-File: LICENSE.txt
